html_classes_obfuscator/__init__.py
html_classes_obfuscator/html_classes_obfuscator.py
html_classes_obfuscator-1.0.1.dist-info/LICENSE
html_classes_obfuscator-1.0.1.dist-info/METADATA
html_classes_obfuscator-1.0.1.dist-info/WHEEL
html_classes_obfuscator-1.0.1.dist-info/top_level.txt
html_classes_obfuscator-1.0.1.dist-info/RECORD
