Metadata-Version: 2.1
Name: html-classes-obfuscator
Version: 1.0.1
Summary: Obfuscate class names in HTML, CSS and Javascript files.
Home-page: https://github.com/xandermann/html-classes-obfuscator
Author: xandermann (Alexandre Hublau)
Author-email: <contact@alexandre-hublau.com>
License: UNKNOWN
Keywords: html,obfuscator
Platform: UNKNOWN
Classifier: Intended Audience :: Developers
Classifier: Programming Language :: Python :: 3
Classifier: Operating System :: Unix
Classifier: Operating System :: MacOS :: MacOS X
Classifier: Operating System :: Microsoft :: Windows
License-File: LICENSE
